pythonvideoannotator_module_deeplab/__init__.py
pythonvideoannotator_module_deeplab/deeplab_window.py
pythonvideoannotator_module_deeplab/module.py
Python_video_annotator_module_deeplab-0.902.21.dist-info/METADATA
Python_video_annotator_module_deeplab-0.902.21.dist-info/WHEEL
Python_video_annotator_module_deeplab-0.902.21.dist-info/top_level.txt
Python_video_annotator_module_deeplab-0.902.21.dist-info/RECORD
