Metadata-Version: 2.1
Name: Python-video-annotator-module-deeplab
Version: 0.902.21
Summary: UNKNOWN
Home-page: https://bitbucket.org/fchampalimaud/pythonvideoannotator-module-deeplab
Author: ['Manuel Manso']
Author-email: manel_manso@hotmail.com
License: UNKNOWN
Platform: UNKNOWN
Requires-Dist: pyyaml
